radkit/__init__.py
radkit/analysis.py
radkit/composition.py
radkit/material.py
radkit/utils.py
radkit/xcom_data.py
radkit-0.1.0.dist-info/licenses/LICENSE.txt
radkit-0.1.0.dist-info/METADATA
radkit-0.1.0.dist-info/WHEEL
radkit-0.1.0.dist-info/top_level.txt
radkit-0.1.0.dist-info/RECORD
