Metadata-Version: 2.4
Name: radkit
Version: 0.1.0
Summary: Photon cross-section and material analysis tools
Author-email: "Charles S. Sosa" <charles.s.sosa@outlook.com>
Requires-Python: >=3.8
License-File: LICENSE.txt
Requires-Dist: dataclasses
Requires-Dist: pandas
Requires-Dist: numpy
Requires-Dist: molmass
Requires-Dist: Tables
Requires-Dist: scipy
Requires-Dist: matplotlib
Requires-Dist: nist-calculators
Requires-Dist: physdata
Requires-Dist: geant4_pybind
Requires-Dist: jupyter
Dynamic: license-file
